schema_alchemist/__init__.py
schema_alchemist/constants.py
schema_alchemist/generators.txt
schema_alchemist/reflection.py
schema_alchemist/utils.py
schema_alchemist/generators/__init__.py
schema_alchemist/generators/base_generators.py
schema_alchemist/generators/column_generators.py
schema_alchemist/generators/relationship_generators.py
schema_alchemist/generators/schema_generators.py
schema_alchemist/generators/table_generators.py
schema_alchemist-0.1.7.dist-info/METADATA
schema_alchemist-0.1.7.dist-info/WHEEL
schema_alchemist-0.1.7.dist-info/licenses/LICENSE
schema_alchemist-0.1.7.dist-info/RECORD
